LICENSE.txt
MANIFEST.in
README.md
setup.py
jk_invoke/AbstractInvoker.py
jk_invoke/CachedPasswordProvider.py
jk_invoke/CommandResult.py
jk_invoke/InteractivePasswordProvider.py
jk_invoke/LocalInvoker.py
jk_invoke/OneSlotPasswordProvider.py
jk_invoke/RemoteInvoker.py
jk_invoke/RemoteSudoInvoker.py
jk_invoke/SSHConnectionProvider.py
jk_invoke/__init__.py
jk_invoke/simple_encrypter.py
jk_invoke.egg-info/PKG-INFO
jk_invoke.egg-info/SOURCES.txt
jk_invoke.egg-info/dependency_links.txt
jk_invoke.egg-info/not-zip-safe
jk_invoke.egg-info/requires.txt
jk_invoke.egg-info/top_level.txt