Metadata-Version: 2.1
Name: jk-invoke
Version: 0.2020.4.6
Summary: This python module provides a high level interface to provide a clean API for executing commands and reading and writing files transparently: It doesn't matter if you operate locally or remotely or as a regular user or as root via sudo.
Home-page: https://github.com/jkpubsrc/python-module-jk-invoke
Author: Jürgen Knauth
Author-email: pubsrc@binary-overflow.de
License: Apache 2.0
Download-URL: https://github.com/jkpubsrc/python-module-jk-invoke/tarball/0.2020.4.6
Keywords: ssh
Platform: UNKNOWN
Classifier: Development Status :: 4 - Beta
Classifier: License :: OSI Approved :: Apache Software License
